{
	"name": "health",
	"plugin-id": "Sprite",
	"sid": 988318597315822,
	"isGlobal": false,
	"instanceVariables": [],
	"behaviorTypes": [],
	"effectTypes": [],
	"animations": {
		"items": [
			{
				"frames": [
					{
						"width": 48,
						"height": 65,
						"originX": 0.5,
						"originY": 1.123076923076923,
						"originalSource": "",
						"exportFormat": "png",
						"exportQuality": 0.8,
						"imageSpriteId": 27273,
						"useCollisionPoly": true,
						"duration": 1
					}
				],
				"sid": 232489252527679,
				"name": "Animation 1",
				"isLooping": false,
				"isPingPong": false,
				"repeatCount": 1,
				"repeatTo": 0,
				"speed": 5
			}
		],
		"subfolders": []
	}
}